minoshiro/__init__.py
minoshiro/enums.py
minoshiro/helpers.py
minoshiro/logger.py
minoshiro/minoshiro.py
minoshiro/pre_cache.py
minoshiro/upstream.py
minoshiro/data/__init__.py
minoshiro/data_controller/__init__.py
minoshiro/data_controller/abc.py
minoshiro/data_controller/constants.py
minoshiro/data_controller/postgres_controller.py
minoshiro/data_controller/postgres_utils.py
minoshiro/data_controller/sqlite_controller.py
minoshiro/data_controller/sqlite_utils.py
minoshiro/web_api/__init__.py
minoshiro/web_api/ani_db.py
minoshiro/web_api/ani_list.py
minoshiro/web_api/anime_planet.py
minoshiro/web_api/kitsu.py
minoshiro/web_api/lndb.py
minoshiro/web_api/mal.py
minoshiro/web_api/mu.py
minoshiro/web_api/nu.py
minoshiro-0.1.7.dist-info/DESCRIPTION.rst
minoshiro-0.1.7.dist-info/METADATA
minoshiro-0.1.7.dist-info/RECORD
minoshiro-0.1.7.dist-info/WHEEL
minoshiro-0.1.7.dist-info/metadata.json
minoshiro-0.1.7.dist-info/top_level.txt
