Metadata-Version: 2.0
Name: minoshiro
Version: 0.1.7
Summary: An async Python3.6 library to search for anime, manga andlight novel using various web apis.
Home-page: https://github.com/Mino-shiro/Minoshiro
Author: MaT1g3R, dashwav
Author-email: UNKNOWN
License: MIT
Platform: UNKNOWN
Classifier: Development Status :: 4 - Beta
Classifier: Framework :: AsyncIO
Classifier: Programming Language :: Python :: 3 :: Only
Classifier: Programming Language :: Python :: 3.6
Classifier: License :: OSI Approved :: MIT License
Classifier: Intended Audience :: Developers
Classifier: Natural Language :: English
Requires-Dist: aiohttp (>=2.2.5)
Requires-Dist: aiohttp-wrapper (>=1.0.0)
Requires-Dist: pyquery (>=1.2.17)
Requires-Dist: xmltodict (>=0.11.0)
Provides-Extra: postgres
Requires-Dist: asyncpg (>=0.12.0); extra == 'postgres'
